config/__init__.py
config/api_provider.py
config/settings.py
core/__init__.py
core/container.py
core/urls_traker.py
core/utils.py
loaders/__init__.py
loaders/base.py
loaders/csv_data_sink.py
loaders/json_data_sink.py
loaders/yaml_data_sink.py
sheared-0.1.2.dist-info/METADATA
sheared-0.1.2.dist-info/WHEEL
sheared-0.1.2.dist-info/top_level.txt
sheared-0.1.2.dist-info/RECORD
